botw_actor_tool/Ui_ActorLink.py
botw_actor_tool/Ui_ActorSelect.py
botw_actor_tool/Ui_Main.py
botw_actor_tool/Ui_Settings.py
botw_actor_tool/Ui_TextEditor.py
botw_actor_tool/Ui_Texts.py
botw_actor_tool/__init__.py
botw_actor_tool/__main__.py
botw_actor_tool/__version__.py
botw_actor_tool/actor.py
botw_actor_tool/actorinfo.py
botw_actor_tool/flag.py
botw_actor_tool/pack.py
botw_actor_tool/store.py
botw_actor_tool/texts.py
botw_actor_tool/util.py
botw_actor_tool/data/generic_link_files.json
botw_actor_tool/data/instSize_data.json
botw_actor_tool/data/keys_by_profile.json
botw_actor_tool/data/overrides.json
botw_actor_tool/data/vanilla_params.json
botw_actor_tool-0.2.11.dist-info/LICENSE
botw_actor_tool-0.2.11.dist-info/METADATA
botw_actor_tool-0.2.11.dist-info/WHEEL
botw_actor_tool-0.2.11.dist-info/entry_points.txt
botw_actor_tool-0.2.11.dist-info/top_level.txt
botw_actor_tool-0.2.11.dist-info/RECORD
