Metadata-Version: 2.1
Name: botw-actor-tool
Version: 0.2.11
Summary: Utility for editing actors in LoZ:BotW
Home-page: https://github.com/GingerAvalanche/botw_actor_tool
Author: Ginger
Author-email: chodness@gmail.com
License: UNKNOWN
Platform: UNKNOWN
Classifier: Programming Language :: Python :: 3.7
Classifier: License :: OSI Approved :: GNU Affero General Public License v3 or later (AGPLv3+)
Classifier: Operating System :: OS Independent
Classifier: Development Status :: 4 - Beta
Requires-Python: >=3.7.4
Requires-Dist: wxPython (>=4.1.0)
Requires-Dist: oead (>=0.11.2)
Requires-Dist: PyMsyt (>=0.3.0)
Requires-Dist: update-check (>=0.0.11)
